forensicface/__init__.py
forensicface/_modidx.py
forensicface/app.py
forensicface/core.py
forensicface/forensicface.py
forensicface/utils.py
forensicface-0.4.1.dist-info/LICENSE
forensicface-0.4.1.dist-info/METADATA
forensicface-0.4.1.dist-info/WHEEL
forensicface-0.4.1.dist-info/entry_points.txt
forensicface-0.4.1.dist-info/top_level.txt
forensicface-0.4.1.dist-info/RECORD
