Metadata-Version: 2.1
Name: forensicface
Version: 0.4.1
Summary: A package for forensic face examination
Home-page: https://github.com/rafribeiro/forensicface
Author: Rafael O. Ribeiro
Author-email: rafaeloliveiraribeiro@gmail.com
License: BSD License
Keywords: nbdev jupyter python face recognition forensics
Classifier: Development Status :: 5 - Production/Stable
Classifier: Intended Audience :: Developers
Classifier: Natural Language :: English
Classifier: Programming Language :: Python :: 3.9
Classifier: Programming Language :: Python :: 3.10
Classifier: License :: OSI Approved :: BSD License
Requires-Python: >=3.9
License-File: LICENSE
Requires-Dist: fastcore
Requires-Dist: nbdev
Requires-Dist: pandas
Requires-Dist: insightface (>0.5)
Requires-Dist: onnxruntime-gpu (>=1.10.0)
Requires-Dist: imutils
Requires-Dist: setuptools
Provides-Extra: dev
